gmtmodernize/__init__.py
gmtmodernize/_version.py
gmtmodernize/cli.py
gmtmodernize/conversion.py
gmtmodernize/tests/__init__.py
gmtmodernize/tests/test_cli.py
gmtmodernize/tests/test_integration.py
gmtmodernize/tests/data/classic/arrows.sh
gmtmodernize/tests/data/classic/bswap16.sh
gmtmodernize/tests/data/classic/grdcontour.sh
gmtmodernize/tests/data/classic/logos.sh
gmtmodernize/tests/data/classic/plot_symbols.sh
gmtmodernize/tests/data/classic/polcontr.sh
gmtmodernize/tests/data/classic/pscoast_JE3.sh
gmtmodernize/tests/data/classic/pscoast_JM.sh
gmtmodernize/tests/data/classic/vector.sh
gmtmodernize/tests/data/classic/wedges.sh
gmtmodernize/tests/data/mirror_directory/not_script.xyz
gmtmodernize/tests/data/mirror_directory/script.sh
gmtmodernize/tests/data/mirror_directory/level1/not_script.txt
gmtmodernize/tests/data/mirror_directory/level1/level2/not_script.txt
gmtmodernize/tests/data/mirror_directory/level1/level2/script.sh
gmtmodernize/tests/data/mirror_directory/subfolder/not_script.foo
gmtmodernize/tests/data/mirror_directory/subfolder/script.sh
gmtmodernize/tests/data/modern/arrows.sh
gmtmodernize/tests/data/modern/bswap16.sh
gmtmodernize/tests/data/modern/grdcontour.sh
gmtmodernize/tests/data/modern/logos.sh
gmtmodernize/tests/data/modern/plot_symbols.sh
gmtmodernize/tests/data/modern/polcontr.sh
gmtmodernize/tests/data/modern/pscoast_JE3.sh
gmtmodernize/tests/data/modern/pscoast_JM.sh
gmtmodernize/tests/data/modern/vector.sh
gmtmodernize/tests/data/modern/wedges.sh
gmtmodernize-1.2.dist-info/DESCRIPTION.rst
gmtmodernize-1.2.dist-info/METADATA
gmtmodernize-1.2.dist-info/RECORD
gmtmodernize-1.2.dist-info/WHEEL
gmtmodernize-1.2.dist-info/entry_points.txt
gmtmodernize-1.2.dist-info/metadata.json
gmtmodernize-1.2.dist-info/top_level.txt
