Metadata-Version: 2.0
Name: gmtmodernize
Version: 1.2
Summary: Tool to convert GMT scripts to the new modern execution mode
Home-page: https://github.com/GenericMappingTools/gmtmodernize
Author: Leonardo Uieda
Author-email: leouieda@gmail.com
License: BSD License
Platform: Any
Classifier: Development Status :: 4 - Beta
Classifier: Intended Audience :: Science/Research
Classifier: Intended Audience :: Developers
Classifier: Intended Audience :: Education
Classifier: Topic :: Scientific/Engineering
Classifier: Topic :: Software Development :: Libraries
Classifier: Programming Language :: Python :: 3.4
Classifier: Programming Language :: Python :: 3.5
Classifier: Programming Language :: Python :: 3.6
Classifier: License :: OSI Approved :: BSD License
Requires-Dist: docopt
